sarathii/__init__.py
sarathii/main.py
sarathii/sarathii.jpg
sarathii-0.8.1.dist-info/licenses/LICENSE.txt
sarathii-0.8.1.dist-info/WHEEL
sarathii-0.8.1.dist-info/METADATA
sarathii-0.8.1.dist-info/RECORD
