Metadata-Version: 2.4
Name: sarathii
Version: 0.8.1
Summary: A sample package published using Flit
Author-email: Vijayasarathi <vijayasarathi871@gmail.com>
Requires-Python: >=3.8
License-File: LICENSE.txt
